rototiller.py
rototiller-0.3.0.dist-info/LICENSE
rototiller-0.3.0.dist-info/METADATA
rototiller-0.3.0.dist-info/WHEEL
rototiller-0.3.0.dist-info/top_level.txt
rototiller-0.3.0.dist-info/RECORD
